{"datasets":[{"data":[9,20,10,23,42,28,15,15,12,0,0,10],"name":"単勝的中率","type":"area","unit":"%","valueDecimals":1,"yAxis":0},{"data":[41,79,85,90,272,135,44,133,295,0,0,25],"name":"単勝回収率","type":"area","unit":"%","valueDecimals":0,"yAxis":0},{"data":[47,45,44,61,65,57,45,42,31,60,54,20],"name":"複勝的中率","type":"area","unit":"%","valueDecimals":0,"yAxis":0},{"data":[101,80,104,93,135,101,80,90,85,153,85,23],"name":"複勝回収率","type":"area","unit":"%","valueDecimals":0,"yAxis":0}],"xData":["01月：◎","02月：◎","03月：◎","04月：◎","05月：◎","06月：◎","07月：◎","08月：◎","09月：◎","10月：◎","11月：◎","12月：◎"]}